{"skeleton":{"hash":"bZGVSB7XLHWieMSTU5nDUA3oMPo","spine":"3.7.94","width":101.32,"height":170.96,"images":"","audio":""},"bones":[{"name":"root","scaleX":0.6,"scaleY":0.6},{"name":"corsslight01","parent":"root","x":-71.2,"y":18.84},{"name":"corsslight02","parent":"root","x":-32.59,"y":-29.82},{"name":"corsslight03","parent":"root","x":-58.51,"y":-99.64},{"name":"corsslight04","parent":"root","x":24.01,"y":-72.67},{"name":"corsslight05","parent":"root","x":57.33,"y":-16.06},{"name":"corsslight06","parent":"root","x":58.39,"y":-99.12},{"name":"eff01","parent":"root","length":84.9,"rotation":90,"x":-55.37,"y":-71.43},{"name":"eff02","parent":"root","length":84.9,"rotation":90,"x":60.87,"y":-46.52},{"name":"eff03","parent":"root","length":84.9,"rotation":90,"x":16.76,"y":-125.93},{"name":"eff04","parent":"root","length":84.9,"rotation":90,"x":37.03,"y":-17.49,"scaleX":0.657,"scaleY":0.34},{"name":"eff05","parent":"root","length":84.9,"rotation":90,"x":-81.3,"y":-36.94,"scaleX":0.657,"scaleY":0.34},{"name":"eff06","parent":"root","length":84.9,"rotation":90,"x":-20.6,"y":-66.76,"scaleX":0.657,"scaleY":0.34},{"name":"eff07","parent":"root","length":84.9,"rotation":90,"x":76.44,"y":-54.83,"scaleX":0.657,"scaleY":0.34},{"name":"ring01","parent":"root"},{"name":"ring02","parent":"root"},{"name":"ring03","parent":"root"},{"name":"spark","parent":"root"},{"name":"starlight","parent":"root"},{"name":"starlight01","parent":"starlight","length":113.2,"rotation":90},{"name":"starlight2","parent":"starlight","length":113.2}],"slots":[{"name":"ring01","bone":"ring01","color":"ffffff00","attachment":"ring01"},{"name":"ring02","bone":"ring02","color":"ffffff00","attachment":"ring02"},{"name":"ring03","bone":"ring03","color":"ffffff00","attachment":"ring03"},{"name":"crosslight","bone":"corsslight01","color":"ffffff00","attachment":"crosslight"},{"name":"crosslight2","bone":"corsslight02","color":"ffffff00","attachment":"crosslight"},{"name":"crosslight3","bone":"corsslight03","color":"ffffff00","attachment":"crosslight"},{"name":"crosslight4","bone":"corsslight04","color":"ffffff00","attachment":"crosslight"},{"name":"crosslight5","bone":"corsslight05","color":"ffffff00","attachment":"crosslight"},{"name":"crosslight6","bone":"corsslight06","color":"ffffff00","attachment":"crosslight"},{"name":"starlight01","bone":"starlight01","color":"ffffff00","attachment":"lightstar"},{"name":"starlight012","bone":"starlight2","color":"ffffff00","attachment":"lightstar"},{"name":"eff01","bone":"eff01","color":"ffffff00","attachment":"eff01"},{"name":"eff012","bone":"eff02","color":"ffffff00","attachment":"eff01"},{"name":"eff0122","bone":"eff03","color":"ffffff00","attachment":"eff01"},{"name":"eff01222","bone":"eff04","color":"ffffff00","attachment":"eff01"},{"name":"eff012222","bone":"eff05","color":"ffffff00","attachment":"eff01"},{"name":"eff0122222","bone":"eff06","color":"ffffff00","attachment":"eff01"},{"name":"eff01222222","bone":"eff07","color":"ffffff00","attachment":"eff01"}],"skins":{"default":{"crosslight":{"crosslight":{"width":37,"height":37}},"crosslight2":{"crosslight":{"width":37,"height":37}},"crosslight3":{"crosslight":{"width":37,"height":37}},"crosslight4":{"crosslight":{"width":37,"height":37}},"crosslight5":{"crosslight":{"width":37,"height":37}},"crosslight6":{"crosslight":{"width":37,"height":37}},"eff01":{"eff01":{"rotation":-90,"width":16,"height":180}},"eff012":{"eff01":{"rotation":-90,"width":16,"height":180}},"eff0122":{"eff01":{"rotation":-90,"width":16,"height":180}},"eff01222":{"eff01":{"rotation":-90,"width":16,"height":180}},"eff012222":{"eff01":{"rotation":-90,"width":16,"height":180}},"eff0122222":{"eff01":{"rotation":-90,"width":16,"height":180}},"eff01222222":{"eff01":{"rotation":-90,"width":16,"height":180}},"ring01":{"ring01":{"scaleX":0.35,"scaleY":0.35,"width":293,"height":290}},"ring02":{"ring02":{"width":94,"height":94}},"ring03":{"ring03":{"width":94,"height":94}},"starlight01":{"lightstar":{"rotation":-90,"width":30,"height":138}},"starlight012":{"lightstar":{"rotation":-90,"width":30,"height":138}}}},"animations":{"animation":{"slots":{"crosslight":{"color":[{"time":0.5,"color":"ffffff00"},{"time":0.6667,"color":"ffffffff","curve":"stepped"},{"time":0.9667,"color":"ffffffff"},{"time":1.1333,"color":"ffffff00"}]},"crosslight3":{"color":[{"time":0,"color":"ffffff00"},{"time":0.2333,"color":"ffffffff"},{"time":0.5,"color":"ffffffb8"},{"time":0.6333,"color":"ffffff00"}]},"crosslight4":{"color":[{"time":0.3,"color":"ffffff00"},{"time":0.5,"color":"ffffffff"},{"time":0.8667,"color":"ffffff79"},{"time":1.1,"color":"ffffff00"}]},"crosslight6":{"color":[{"time":0.1667,"color":"ffffff00"},{"time":0.3667,"color":"ffffffff"},{"time":0.6667,"color":"ffffffa3"},{"time":0.8333,"color":"ffffff00"}]},"eff01":{"color":[{"time":0.3333,"color":"ffffff00"},{"time":0.5,"color":"ffffffff","curve":"stepped"},{"time":0.8333,"color":"ffffffff"},{"time":1,"color":"ffffff00"}]},"eff012":{"color":[{"time":0.3,"color":"ffffff00"},{"time":0.4333,"color":"ffffffff","curve":"stepped"},{"time":0.5333,"color":"ffffffff"},{"time":0.7667,"color":"ffffff00"}]},"eff0122":{"color":[{"time":0,"color":"ffffff00"},{"time":0.0667,"color":"ffffff3f"},{"time":0.1667,"color":"ffffffff","curve":"stepped"},{"time":0.5,"color":"ffffffff"},{"time":0.6667,"color":"ffffff00"}]},"eff012222":{"color":[{"time":0,"color":"ffffff00"},{"time":0.137,"color":"ffffffff","curve":"stepped"},{"time":0.2555,"color":"ffffffff"},{"time":0.3888,"color":"ffffff00"}]},"eff0122222":{"color":[{"time":0.5333,"color":"ffffff00"},{"time":0.6667,"color":"ffffffff","curve":"stepped"},{"time":0.8667,"color":"ffffffff"},{"time":1,"color":"ffffff00"}]},"eff01222222":{"color":[{"time":0.6667,"color":"ffffff00"},{"time":0.8,"color":"ffffffff","curve":"stepped"},{"time":1,"color":"ffffffff"},{"time":1.2,"color":"ffffff00"}]},"ring01":{"color":[{"time":0,"color":"ffffff00"},{"time":0.1667,"color":"ffffffff"},{"time":0.6667,"color":"ffffff00"}]},"ring02":{"color":[{"time":0,"color":"ffffff00"},{"time":0.0667,"color":"ffffffff","curve":"stepped"},{"time":0.1667,"color":"ffffffff"},{"time":0.4667,"color":"c7ff8aff"},{"time":0.6667,"color":"ffffff00"}]},"ring03":{"color":[{"time":0.1,"color":"ffffff00"},{"time":0.1333,"color":"ffffffff","curve":"stepped"},{"time":0.5667,"color":"ffffffff"},{"time":1,"color":"1d822700"}]}},"bones":{"corsslight01":{"translate":[{"time":0,"x":45.2,"y":-184.11},{"time":0.5,"x":45.2,"y":-187.05,"curve":[0.215,0.9,0.672,0.91]},{"time":1.1333,"x":45.2,"y":127.94},{"time":1.2,"x":45.2,"y":0}],"scale":[{"time":0.5,"x":1,"y":1,"curve":[0.135,0.86,0.61,0.9]},{"time":1.1333,"x":1.8,"y":1.8},{"time":1.2,"x":1,"y":1}]},"corsslight03":{"translate":[{"time":0,"x":0,"y":0},{"time":0.6333,"x":0,"y":161.9}]},"corsslight04":{"translate":[{"time":0.3,"x":0,"y":0,"curve":[0.224,0.76,0.37,0.95]},{"time":1.1,"x":0,"y":164.02},{"time":1.2,"x":0,"y":0}],"scale":[{"time":0.3,"x":1,"y":1,"curve":[0.198,1,0.61,0.85]},{"time":1.1,"x":1.839,"y":1.839},{"time":1.2,"x":1,"y":1}]},"corsslight06":{"translate":[{"time":0.1667,"x":0,"y":0,"curve":[0.178,0.78,0.527,1]},{"time":0.8333,"x":0,"y":219.84}],"scale":[{"time":0.1667,"x":1,"y":1,"curve":[0.178,0.75,0.567,1]},{"time":0.8333,"x":1.85,"y":1.85},{"time":1.2,"x":1,"y":1}]},"eff01":{"translate":[{"time":0,"x":0,"y":-83.11},{"time":0.3333,"x":0,"y":-130.02},{"time":0.3667,"x":0,"y":-72.03},{"time":1,"x":0,"y":293.23}],"scale":[{"time":0.3333,"x":1,"y":1},{"time":0.3667,"x":0.249,"y":1},{"time":0.5,"x":1,"y":1,"curve":"stepped"},{"time":0.8333,"x":1,"y":1},{"time":1,"x":0.598,"y":1}]},"eff02":{"translate":[{"time":0,"x":0,"y":0},{"time":0.3,"x":0,"y":-201.19,"curve":[0.181,0.72,0.424,0.8]},{"time":0.9333,"x":0,"y":132.5}],"scale":[{"time":0,"x":1,"y":1},{"time":0.3,"x":0.249,"y":1},{"time":0.4333,"x":1,"y":1,"curve":"stepped"},{"time":0.7667,"x":1,"y":1},{"time":0.9333,"x":0.598,"y":1}]},"eff03":{"translate":[{"time":0,"x":0,"y":-72.03},{"time":0.6667,"x":0,"y":293.23}],"scale":[{"time":0.5,"x":1,"y":1},{"time":0.6667,"x":0.598,"y":1}]},"eff04":{"scale":[{"time":0,"x":0.999,"y":1}]},"eff05":{"translate":[{"time":0,"x":0,"y":-49.56},{"time":0.3888,"x":0,"y":149.12}],"scale":[{"time":0,"x":0.999,"y":1}]},"eff06":{"translate":[{"time":0,"x":0,"y":-111.99,"curve":"stepped"},{"time":0.5333,"x":0,"y":-111.99,"curve":[0.227,0.69,0.478,0.86]},{"time":1,"x":0,"y":135.84}],"scale":[{"time":0,"x":0.999,"y":1}]},"eff07":{"translate":[{"time":0.6667,"x":0,"y":0},{"time":1.2,"x":0,"y":268.71}],"scale":[{"time":0,"x":0.999,"y":1},{"time":0.6667,"x":0.667,"y":1},{"time":0.8,"x":0.999,"y":1}]},"ring01":{"scale":[{"time":0,"x":0,"y":0,"curve":[0.284,1,0.518,0.94]},{"time":0.6667,"x":2.193,"y":2.193}]},"ring02":{"scale":[{"time":0,"x":0,"y":0},{"time":0.6667,"x":2.5,"y":2.5}]},"ring03":{"scale":[{"time":0.1333,"x":1,"y":1,"curve":[0.261,0.35,0.378,0.79]},{"time":1,"x":4.268,"y":4.268}]},"starlight01":{"scale":[{"time":0,"x":1,"y":2},{"time":0.4,"x":1,"y":0.265}]},"starlight2":{"scale":[{"time":0,"x":1,"y":2},{"time":1.2,"x":1,"y":0.265}]},"spark":{"scale":[{"time":0,"x":0.02,"y":0.02},{"time":0.4667,"x":1,"y":1},{"time":0.5,"x":0,"y":0}]},"starlight":{"scale":[{"time":0,"x":0.299,"y":0.299,"curve":[0.201,1,0.632,0.9]},{"time":1.2,"x":0,"y":0}]}}}}}