{"skeleton":{"hash":"jL1cn3E9tcBD5Fv5XPuJrarQrxw","spine":"3.7.94","width":197.6,"height":223.2,"images":"","audio":""},"bones":[{"name":"root","scaleX":0.4,"scaleY":0.4},{"name":"move","parent":"root","x":-75.74},{"name":"shield","parent":"move","length":210,"y":1},{"name":"shield2","parent":"move","length":184,"rotation":-180,"x":231.5}],"slots":[{"name":"shield2","bone":"shield2","attachment":"light"},{"name":"shield","bone":"shield","attachment":"shield"}],"skins":{"default":{"shield":{"shield":{"x":138.99,"y":-1,"width":197,"height":442}},"shield2":{"light":{"x":153.99,"scaleX":2,"scaleY":2,"rotation":180,"width":247,"height":279}}}},"animations":{"animation":{"slots":{"shield2":{"color":[{"time":0,"color":"ffffffc7"},{"time":0.8333,"color":"ffffffff"},{"time":1.6667,"color":"ffffffc8"}]}},"bones":{"shield2":{"scale":[{"time":0,"x":0.892,"y":1,"curve":[0.198,0.66,0.75,1]},{"time":0.8333,"x":1.246,"y":1.246},{"time":1.6667,"x":0.892,"y":1}]},"root":{"scale":[{"time":1.6667,"x":1,"y":1},{"time":2.6,"x":0.99,"y":0.99}]}}}}}