{"skeleton":{"hash":"ZCqtGFlZaRZfpnqel0tPHdCZvvs","spine":"3.7.94","width":132,"height":130,"images":"../images/","audio":"V:/nvzhu/images"},"bones":[{"name":"root"},{"name":"shoes","parent":"root"}],"slots":[{"name":"shoes","bone":"root","attachment":"shoes2"}],"skins":{"default":{"shoes":{"shoes2":{"type":"mesh","uvs":[1,1,0,1,0,0,1,0],"triangles":[1,2,3,1,3,0],"vertices":[1,1,67.98,-59.59,1,1,1,-64.02,-59.59,1,1,1,-64.02,70.41,1,1,1,67.98,70.41,1],"hull":4,"edges":[0,2,2,4,4,6,0,6],"width":132,"height":130}}}},"animations":{"animation":{"bones":{"root":{"shear":[{"time":2.6667,"x":0,"y":0}]}}}}}